README.md
setup.py
aiosmpp/__init__.py
aiosmpp/client.py
aiosmpp/command.py
aiosmpp/command_codes.py
aiosmpp/consts.py
aiosmpp/exceptions.py
aiosmpp/gsm.py
aiosmpp/pdu.py
aiosmpp/ptypes.py
aiosmpp/smpp.py
aiosmpp.egg-info/PKG-INFO
aiosmpp.egg-info/SOURCES.txt
aiosmpp.egg-info/dependency_links.txt
aiosmpp.egg-info/requires.txt
aiosmpp.egg-info/top_level.txt
aiosmpp.egg-info/zip-safe
tests/__init__.py
tests/test_gsm.py